pyrochain/__init__.py
pyrochain/cli.py
pyrochain/core.py
pyrochain/__pycache__/__init__.cpython-312.pyc
pyrochain/__pycache__/core.cpython-312.pyc
pyrochain/adapters/__init__.py
pyrochain/adapters/adapter.py
pyrochain/adapters/base.py
pyrochain/adapters/lora.py
pyrochain/adapters/__pycache__/__init__.cpython-312.pyc
pyrochain/adapters/__pycache__/adapter.cpython-312.pyc
pyrochain/adapters/__pycache__/base.cpython-312.pyc
pyrochain/adapters/__pycache__/lora.cpython-312.pyc
pyrochain/agents/__init__.py
pyrochain/agents/base.py
pyrochain/agents/feature_agent.py
pyrochain/agents/validation_agent.py
pyrochain/agents/__pycache__/__init__.cpython-312.pyc
pyrochain/agents/__pycache__/base.cpython-312.pyc
pyrochain/agents/__pycache__/feature_agent.cpython-312.pyc
pyrochain/agents/__pycache__/validation_agent.cpython-312.pyc
pyrochain/chains/__init__.py
pyrochain/chains/base.py
pyrochain/chains/feature_extraction_chain.py
pyrochain/chains/validation_chain.py
pyrochain/chains/__pycache__/__init__.cpython-312.pyc
pyrochain/chains/__pycache__/base.cpython-312.pyc
pyrochain/chains/__pycache__/feature_extraction_chain.cpython-312.pyc
pyrochain/chains/__pycache__/validation_chain.cpython-312.pyc
pyrochain/processors/__init__.py
pyrochain/processors/base.py
pyrochain/processors/image.py
pyrochain/processors/multimodal.py
pyrochain/processors/text.py
pyrochain/processors/__pycache__/__init__.cpython-312.pyc
pyrochain/processors/__pycache__/base.cpython-312.pyc
pyrochain/processors/__pycache__/image.cpython-312.pyc
pyrochain/processors/__pycache__/multimodal.cpython-312.pyc
pyrochain/processors/__pycache__/text.cpython-312.pyc
pyrochain/utils/__init__.py
pyrochain/utils/ecommerce.py
pyrochain/utils/metrics.py
pyrochain/utils/visualization.py
pyrochain-0.1.0.dist-info/licenses/LICENSE
pyrochain-0.1.0.dist-info/METADATA
pyrochain-0.1.0.dist-info/WHEEL
pyrochain-0.1.0.dist-info/entry_points.txt
pyrochain-0.1.0.dist-info/top_level.txt
pyrochain-0.1.0.dist-info/RECORD
