Metadata-Version: 2.4
Name: pyrochain
Version: 0.1.0
Summary: PyTorch + LangChain for Agentic Feature Engineering
Home-page: https://github.com/irfanalidv/PyroChain
Author: Irfan Ali
Maintainer: Irfan Ali
License-Expression: MIT
Project-URL: Homepage, https://github.com/irfanalidv/PyroChain
Project-URL: Documentation, https://github.com/irfanalidv/PyroChain#readme
Project-URL: Repository, https://github.com/irfanalidv/PyroChain.git
Project-URL: Bug Tracker, https://github.com/irfanalidv/PyroChain/issues
Project-URL: Changelog, https://github.com/irfanalidv/PyroChain/blob/main/CHANGELOG.md
Keywords: pytorch,langchain,feature-engineering,machine-learning,multimodal,agents,llm,adapters,ecommerce
Classifier: Development Status :: 3 - Alpha
Classifier: Intended Audience :: Developers
Classifier: Intended Audience :: Science/Research
Classifier: Operating System :: OS Independent
Classifier: Programming Language :: Python :: 3
Classifier: Programming Language :: Python :: 3.8
Classifier: Programming Language :: Python :: 3.9
Classifier: Programming Language :: Python :: 3.10
Classifier: Programming Language :: Python :: 3.11
Classifier: Topic :: Scientific/Engineering :: Artificial Intelligence
Classifier: Topic :: Software Development :: Libraries :: Python Modules
Requires-Python: >=3.8
License-File: LICENSE
Requires-Dist: torch>=2.0.0
Requires-Dist: transformers>=4.30.0
Requires-Dist: langchain>=0.1.0
Requires-Dist: langchain-community>=0.0.20
Requires-Dist: langchain-experimental>=0.0.40
Requires-Dist: numpy>=1.21.0
Requires-Dist: pandas>=1.3.0
Requires-Dist: Pillow>=8.0.0
Requires-Dist: opencv-python>=4.5.0
Requires-Dist: datasets>=2.0.0
Requires-Dist: textblob>=0.17.0
Requires-Dist: nltk>=3.8.0
Requires-Dist: chromadb>=0.4.0
Requires-Dist: sentence-transformers>=2.2.0
Requires-Dist: faiss-cpu>=1.7.0
Requires-Dist: redis>=4.0.0
Requires-Dist: pydantic>=2.0.0
Requires-Dist: tqdm>=4.60.0
Requires-Dist: python-dotenv>=0.19.0
Requires-Dist: click>=8.0.0
Requires-Dist: rich>=12.0.0
Requires-Dist: scikit-learn>=1.0.0
Requires-Dist: matplotlib>=3.5.0
Requires-Dist: seaborn>=0.11.0
Provides-Extra: dev
Requires-Dist: pytest>=6.0; extra == "dev"
Requires-Dist: pytest-cov>=2.0; extra == "dev"
Requires-Dist: black>=21.0; extra == "dev"
Requires-Dist: flake8>=3.8; extra == "dev"
Requires-Dist: mypy>=0.800; extra == "dev"
Requires-Dist: pre-commit>=2.0; extra == "dev"
Requires-Dist: jupyter>=1.0.0; extra == "dev"
Requires-Dist: ipykernel>=6.0.0; extra == "dev"
Provides-Extra: docs
Requires-Dist: sphinx>=4.0; extra == "docs"
Requires-Dist: sphinx-rtd-theme>=1.0; extra == "docs"
Requires-Dist: myst-parser>=0.15; extra == "docs"
Requires-Dist: sphinx-autodoc-typehints>=1.12.0; extra == "docs"
Provides-Extra: gpu
Requires-Dist: torch-audio>=2.0.0; extra == "gpu"
Requires-Dist: torchvision>=0.15.0; extra == "gpu"
Dynamic: home-page
Dynamic: license-file
Dynamic: requires-python
